{
	"info": {
		"_postman_id": "8cc676ad-30f1-4041-b14e-fa5cc543d560",
		"name": "Dummy Api",
		"schema": "https://schema.getpostman.com/json/collection/v2.1.0/collection.json"
	},
	"item": [
		{
			"name": "Get all employee data",
			"request": {
				"method": "GET",
				"header": [],
				"url": {
					"raw": "http://dummy.restapiexample.com/api/v1/employees",
					"protocol": "http",
					"host": [
						"dummy",
						"restapiexample",
						"com"
					],
					"path": [
						"api",
						"v1",
						"employees"
					]
				}
			},
			"response": []
		},
		{
			"name": "Get a single employee data",
			"request": {
				"method": "GET",
				"header": [],
				"url": {
					"raw": "http://dummy.restapiexample.com/api/v1/employee/1",
					"protocol": "http",
					"host": [
						"dummy",
						"restapiexample",
						"com"
					],
					"path": [
						"api",
						"v1",
						"employee",
						"1"
					]
				}
			},
			"response": []
		},
		{
			"name": "create a record",
			"request": {
				"method": "POST",
				"header": [],
				"body": {
					"mode": "raw",
					"raw": "{\"name\":\"test\",\"salary\":\"123\",\"age\":\"24\"}",
					"options": {
						"raw": {
							"language": "json"
						}
					}
				},
				"url": {
					"raw": "http://dummy.restapiexample.com/api/v1/create",
					"protocol": "http",
					"host": [
						"dummy",
						"restapiexample",
						"com"
					],
					"path": [
						"api",
						"v1",
						"create"
					]
				}
			},
			"response": []
		},
		{
			"name": "Update an employee record",
			"request": {
				"method": "PUT",
				"header": [],
				"body": {
					"mode": "raw",
					"raw": " {\r\n        \"name\": \"test\",\r\n        \"salary\": \"123\",\r\n        \"age\": \"28\"\r\n    }",
					"options": {
						"raw": {
							"language": "json"
						}
					}
				},
				"url": {
					"raw": "http://dummy.restapiexample.com/api/v1/update/2472\t",
					"protocol": "http",
					"host": [
						"dummy",
						"restapiexample",
						"com"
					],
					"path": [
						"api",
						"v1",
						"update",
						"2472\t"
					]
				}
			},
			"response": []
		},
		{
			"name": "Delete an employee record",
			"request": {
				"method": "DELETE",
				"header": [],
				"url": {
					"raw": "http://dummy.restapiexample.com/api/v1/delete/2",
					"protocol": "http",
					"host": [
						"dummy",
						"restapiexample",
						"com"
					],
					"path": [
						"api",
						"v1",
						"delete",
						"2"
					]
				}
			},
			"response": []
		}
	]
}